LICENSE.txt
MANIFEST.in
setup.cfg
setup.py
tagarela/__init__.py
tagarela/app.py
tagarela/extensions.py
tagarela/models.py
tagarela/views.py
tagarela.egg-info/PKG-INFO
tagarela.egg-info/SOURCES.txt
tagarela.egg-info/dependency_links.txt
tagarela.egg-info/requires.txt
tagarela.egg-info/top_level.txt